shellextools/LICENSE
shellextools/README.md
shellextools/__init__.py
shellextools/getmultifiles.py
shellextools/loggax3.py
shellextools/requirements.txt
shellextools/thirdparty.json
shellextools-0.15.dist-info/LICENSE.rst
shellextools-0.15.dist-info/METADATA
shellextools-0.15.dist-info/WHEEL
shellextools-0.15.dist-info/top_level.txt
shellextools-0.15.dist-info/RECORD
