Metadata-Version: 2.1
Name: shellextools
Version: 0.15
Summary: Adds Python functions/methods to the Windows context menu
Home-page: https://github.com/hansalemaos/shellextools
Author: Johannes Fischer
Author-email: aulasparticularesdealemaosp@gmail.com
License: MIT
Keywords: Windows context menu,python,nutika
Classifier: Development Status :: 4 - Beta
Classifier: Programming Language :: Python :: 3 :: Only
Classifier: Programming Language :: Python :: 3.10
Classifier: Topic :: Software Development :: Libraries :: Python Modules
Classifier: Topic :: Utilities
License-File: LICENSE.rst
Requires-Dist: amiadmin
Requires-Dist: ctypestoast
Requires-Dist: downloadunzip
Requires-Dist: escape-windows-filepath
Requires-Dist: flatten-any-dict-iterable-or-whatsoever
Requires-Dist: flatten-everything
Requires-Dist: hackyargparser
Requires-Dist: isiter
Requires-Dist: list-all-files-recursively
Requires-Dist: lockexclusive
Requires-Dist: ordered-set
Requires-Dist: reggisearch
Requires-Dist: tolerant-isinstance
Requires-Dist: touchtouch
